{
  "generatedAt": "2026-05-03T15:40:19.220Z",
  "baseUrl": "http://127.0.0.1:8000",
  "buildId": "frontend-39bc0b9be33d",
  "deploymentId": "",
  "assetFqn": "finance_prod.curated.revenue_daily",
  "mockApi": false,
  "evidenceKind": "runtime_app_capture",
  "mockEvidenceWarning": "",
  "liveDatabricksCapture": false,
  "forwardedActorCapture": true,
  "forwardedActorEmail": "skyler@entrada.ai",
  "forwardedActorTokenPresent": false,
  "routeFilter": [
    "discover"
  ],
  "interactionFilter": [
    "selected"
  ],
  "routeFilterUnknown": [],
  "selectedRoutes": [
    "discover"
  ],
  "viewports": [
    {
      "name": "3037x1269",
      "width": 3037,
      "height": 1269
    }
  ],
  "expectedCaptureCount": 1,
  "captures": [
    {
      "route": "discover",
      "path": "/discover",
      "viewport": "3037x1269",
      "loaded": true,
      "screenshot": "docs/northstar_visual_qa/live-runtime-current-v86-wide-selected-finance-shell-2026-05-03/discover-3037x1269.png",
      "fullPageScreenshot": "docs/northstar_visual_qa/live-runtime-current-v86-wide-selected-finance-shell-2026-05-03/discover-3037x1269-full.png",
      "wait": {
        "settleSelectorMatched": true,
        "shellReady": true,
        "readiness": {
          "blockedText": "",
          "disabledAtlasLabels": []
        }
      },
      "metrics": {
        "title": "Governance Atlas",
        "url": "http://127.0.0.1:8000/discovery",
        "readyState": "complete",
        "viewport": {
          "width": 3037,
          "height": 1269,
          "devicePixelRatio": 1
        },
        "scroll": {
          "documentHeight": 1269,
          "documentWidth": 3037,
          "hasVerticalOverflow": false,
          "hasHorizontalOverflow": false
        },
        "shell": {
          "top": 0,
          "left": 298,
          "right": 3037,
          "bottom": 70,
          "width": 2739,
          "height": 70
        },
        "sideRail": {
          "top": 0,
          "left": 0,
          "right": 298,
          "bottom": 1269,
          "width": 298,
          "height": 1269
        },
        "main": {
          "top": 70,
          "left": 298,
          "right": 3037,
          "bottom": 1269,
          "width": 2739,
          "height": 1199
        },
        "mainScroll": {
          "scrollTop": 0,
          "scrollHeight": 6633,
          "clientHeight": 1199,
          "hasOverflow": true
        },
        "home": null,
        "discovery": {
          "top": 70,
          "left": 547.5,
          "right": 2307.5,
          "bottom": 6703.453125,
          "width": 1760,
          "height": 6633.453125
        },
        "entity": null,
        "lineage": null,
        "lineagePrototype": {
          "page": null,
          "hero": null,
          "workbench": null,
          "graph": null
        },
        "audit": {
          "page": null,
          "shell": null,
          "main": null,
          "table": null,
          "mainStyle": null,
          "shellStyle": null
        },
        "admin": {
          "page": null,
          "shell": null,
          "main": null
        },
        "textPreview": "Governance Atlas BY ENTRADA GOVERN Command Center Discover Stewardship KNOWLEDGE Glossary & CDEs Lineage Atlas TRUST Audit Evidence Control Center S Skyler Admin Workspace › datapact.atlas ⌘K UC connected · 100% coverage Atlas AI WORKSPACE-SCOPED METADATA Workspace-scoped app-principal view; actor-scoped protected reads stay restricted. CERTIFICATION 50 results Certified 44 In Review 0 Uncertified 0 Draft 3 DOMAIN Customer 11 Finance 17 Marketing 6 Operations 3 People 1 Product 6 CLASSIFICATION Confidential 45 Internal 1 Restricted 4 ATTRIBUTES Critical Data Element Contains PII No PII DISCOVER Find trusted, governed data Search across catalogs, schemas, tables, columns, models, and glossary terms. Workspace-scoped results use Unity Catalog and governance store signals; actor-scoped protected reads remain restricted. Saved searches Advanced Showing 50 of 50 assets Sort: Relevance risk_policy_exception_register datapact.enterprise_metadata_ops.risk_policy_exception_register Certified 100% 100% Restricted — Aggregated policy-exception register derived from Cotality lien records. Risk Steward ⋮ Open Record Open lineage Certified risk_data_quality_review datapact.enterprise_metadata_ops.risk_data_quality_review Draft 100% 100% Restricted — Aggregated data-quality review signal derived from Cotality market records. Risk Steward ⋮ Open Record Open lineage Draft operations_certification_backlog datapact.enterprise_metadata_ops.operations_certification_backlog Draft 100% 100% Confidential — Aggregated certification backlog signal derived from Cotality transfer records. Operations S",
        "controls": [
          {
            "text": "Command Center",
            "disabled": false,
            "aria": ""
          },
          {
            "text": "Discover",
            "disabled": false,
            "aria": ""
          },
          {
            "text": "Stewardship",
            "disabled": false,
            "aria": ""
          },
          {
            "text": "Glossary & CDEs",
            "disabled": false,
            "aria": ""
          },
          {
            "text": "Lineage Atlas",
            "disabled": false,
            "aria": ""
          },
          {
            "text": "Audit Evidence",
            "disabled": false,
            "aria": ""
          },
          {
            "text": "Control Center",
            "disabled": false,
            "aria": ""
          },
          {
            "text": "S Skyler Admin",
            "disabled": false,
            "aria": "Open profile menu for Skyler"
          },
          {
            "text": "Workspace › datapact.atlas",
            "disabled": false,
            "aria": "Open Governance Atlas Command Center"
          },
          {
            "text": "Submit global search unavailable: enter a search term.",
            "disabled": true,
            "aria": "Submit global search unavailable: enter a search term."
          },
          {
            "text": "Notifications",
            "disabled": false,
            "aria": "Notifications"
          },
          {
            "text": "Help",
            "disabled": false,
            "aria": "Help"
          },
          {
            "text": "Atlas AI",
            "disabled": false,
            "aria": ""
          },
          {
            "text": "Certified 44",
            "disabled": false,
            "aria": ""
          },
          {
            "text": "In Review 0",
            "disabled": false,
            "aria": ""
          },
          {
            "text": "Uncertified 0",
            "disabled": false,
            "aria": ""
          },
          {
            "text": "Draft 3",
            "disabled": false,
            "aria": ""
          },
          {
            "text": "Customer 11",
            "disabled": false,
            "aria": ""
          },
          {
            "text": "Finance 17",
            "disabled": false,
            "aria": ""
          },
          {
            "text": "Marketing 6",
            "disabled": false,
            "aria": ""
          },
          {
            "text": "Operations 3",
            "disabled": false,
            "aria": ""
          },
          {
            "text": "People 1",
            "disabled": false,
            "aria": ""
          },
          {
            "text": "Product 6",
            "disabled": false,
            "aria": ""
          },
          {
            "text": "Confidential 45",
            "disabled": false,
            "aria": ""
          },
          {
            "text": "Internal 1",
            "disabled": false,
            "aria": ""
          },
          {
            "text": "Restricted 4",
            "disabled": false,
            "aria": ""
          },
          {
            "text": "Critical Data Element",
            "disabled": false,
            "aria": ""
          },
          {
            "text": "Contains PII",
            "disabled": false,
            "aria": ""
          },
          {
            "text": "No PII",
            "disabled": false,
            "aria": ""
          },
          {
            "text": "Saved searches",
            "disabled": false,
            "aria": ""
          },
          {
            "text": "Advanced",
            "disabled": false,
            "aria": ""
          },
          {
            "text": "Relevance",
            "disabled": false,
            "aria": ""
          },
          {
            "text": "Grid view",
            "disabled": false,
            "aria": "Grid view"
          },
          {
            "text": "List view",
            "disabled": false,
            "aria": "List view"
          },
          {
            "text": "risk_policy_exception_register",
            "disabled": false,
            "aria": ""
          },
          {
            "text": "Open Record",
            "disabled": false,
            "aria": "Open Record"
          },
          {
            "text": "Open lineage",
            "disabled": false,
            "aria": "Open Lineage"
          },
          {
            "text": "risk_data_quality_review",
            "disabled": false,
            "aria": ""
          },
          {
            "text": "Open Record",
            "disabled": false,
            "aria": "Open Record"
          },
          {
            "text": "Open lineage",
            "disabled": false,
            "aria": "Open Lineage"
          },
          {
            "text": "operations_certification_backlog",
            "disabled": false,
            "aria": ""
          },
          {
            "text": "Open Record",
            "disabled": false,
            "aria": "Open Record"
          },
          {
            "text": "Open lineage",
            "disabled": false,
            "aria": "Open Lineage"
          },
          {
            "text": "finance_exception_review",
            "disabled": false,
            "aria": ""
          },
          {
            "text": "Open Record",
            "disabled": false,
            "aria": "Open Record"
          },
          {
            "text": "Open lineage",
            "disabled": false,
            "aria": "Open Lineage"
          },
          {
            "text": "customer_stewardship_queue",
            "disabled": false,
            "aria": ""
          },
          {
            "text": "Open Record",
            "disabled": false,
            "aria": "Open Record"
          },
          {
            "text": "Open lineage",
            "disabled": false,
            "aria": "Open Lineage"
          },
          {
            "text": "sales_pipeline_revenue",
            "disabled": false,
            "aria": ""
          },
          {
            "text": "Open Record",
            "disabled": false,
            "aria": "Open Record"
          },
          {
            "text": "Open lineage",
            "disabled": false,
            "aria": "Open Lineage"
          },
          {
            "text": "revenue_booking_bridge",
            "disabled": false,
            "aria": ""
          },
          {
            "text": "Open Record",
            "disabled": false,
            "aria": "Open Record"
          },
          {
            "text": "Open lineage",
            "disabled": false,
            "aria": "Open Lineage"
          },
          {
            "text": "orders",
            "disabled": false,
            "aria": ""
          },
          {
            "text": "Open Record",
            "disabled": false,
            "aria": "Open Record"
          },
          {
            "text": "Open lineage",
            "disabled": false,
            "aria": "Open Lineage"
          },
          {
            "text": "revenue_product_signal",
            "disabled": false,
            "aria": ""
          },
          {
            "text": "Open Record",
            "disabled": false,
            "aria": "Open Record"
          },
          {
            "text": "Open lineage",
            "disabled": false,
            "aria": "Open Lineage"
          },
          {
            "text": "product_revenue_experiment_feed",
            "disabled": false,
            "aria": ""
          },
          {
            "text": "Open Record",
            "disabled": false,
            "aria": "Open Record"
          },
          {
            "text": "Open lineage",
            "disabled": false,
            "aria": "Open Lineage"
          },
          {
            "text": "clickstream_events",
            "disabled": false,
            "aria": ""
          },
          {
            "text": "Open Record",
            "disabled": false,
            "aria": "Open Record"
          },
          {
            "text": "Open lineage",
            "disabled": false,
            "aria": "Open Lineage"
          },
          {
            "text": "revenue_attribution_snapshot",
            "disabled": false,
            "aria": ""
          },
          {
            "text": "Open Record",
            "disabled": false,
            "aria": "Open Record"
          },
          {
            "text": "Open lineage",
            "disabled": false,
            "aria": "Open Lineage"
          },
          {
            "text": "campaign_roi_revenue",
            "disabled": false,
            "aria": ""
          },
          {
            "text": "Open Record",
            "disabled": false,
            "aria": "Open Record"
          },
          {
            "text": "Open lineage",
            "disabled": false,
            "aria": "Open Lineage"
          },
          {
            "text": "attribution_daily",
            "disabled": false,
            "aria": ""
          },
          {
            "text": "Open Record",
            "disabled": false,
            "aria": "Open Record"
          },
          {
            "text": "Open lineage",
            "disabled": false,
            "aria": "Open Lineage"
          },
          {
            "text": "compensation_band",
            "disabled": false,
            "aria": ""
          },
          {
            "text": "Open Record",
            "disabled": false,
            "aria": "Open Record"
          },
          {
            "text": "Open lineage",
            "disabled": false,
            "aria": "Open Lineage"
          },
          {
            "text": "payments",
            "disabled": false,
            "aria": ""
          }
        ]
      },
      "shellFallbackUsed": false
    }
  ],
  "interactions": [
    {
      "route": "discover",
      "path": "/discover",
      "viewport": "3037x1269",
      "interaction": "selected",
      "description": "Select the first Discover result and show the asset preview pane.",
      "loaded": true,
      "screenshot": "docs/northstar_visual_qa/live-runtime-current-v86-wide-selected-finance-shell-2026-05-03/discover-selected-3037x1269.png",
      "fullPageScreenshot": "docs/northstar_visual_qa/live-runtime-current-v86-wide-selected-finance-shell-2026-05-03/discover-selected-3037x1269-full.png",
      "runResult": {
        "selectedAssetFqn": "datapact.enterprise_metadata_ops.risk_policy_exception_register"
      },
      "validation": {
        "loaded": true,
        "previewOpen": true,
        "previewVisible": true,
        "selectedAssetFqn": "datapact.enterprise_metadata_ops.risk_policy_exception_register",
        "previewText": "risk_policy_exception_registerCertifiedRestrictedView · datapact.enterprise_metadata_ops.risk_policy_exception_register×Open Asset 360Open LineageGovernanceLive rows unavailableAsset preview and sample data require per-user authorization / OBO; app-principal fallback does not widen user-visible data.Certified100% Metadata CoverageRestrictedOverviewColumns · 0LineageQualityAccessAggregated policy-exception register derived from Cotality lien records.MetadataOwnerRisk StewardSteward teamUnavailableFreshnessUnavailableQuality scoreUnavailableRowsUnavailableUsage · 30dUnavailableConnected AssetsNo live upstream lineage edges are surfaced for this asset yet.Tags & Glossarycertification=Certifiedcriticality=Criticaldata_product=Risk Controlsdomain=Riskglossary_term=Net Revenue+2 moreBuildability NoteThis read-only preview uses available Discover and Asset 360 fields; it is not workflow mutation evidence. Unsupported workflow actions remain unavailable here.Comment and access-request creation",
        "nonAuthoritativeNotice": false,
        "honestPreviewState": true,
        "livePreviewOverclaim": false,
        "controls": [
          {
            "text": "×",
            "disabled": false
          },
          {
            "text": "Open Asset 360",
            "disabled": false
          },
          {
            "text": "Open Lineage",
            "disabled": false
          },
          {
            "text": "Governance",
            "disabled": false
          },
          {
            "text": "Overview",
            "disabled": false
          },
          {
            "text": "Columns · 0",
            "disabled": false
          },
          {
            "text": "Lineage",
            "disabled": false
          },
          {
            "text": "Quality",
            "disabled": false
          },
          {
            "text": "Access",
            "disabled": false
          },
          {
            "text": "Comment",
            "disabled": true
          },
          {
            "text": "Request access",
            "disabled": true
          },
          {
            "text": "Certify",
            "disabled": false
          }
        ]
      },
      "metrics": {
        "title": "Governance Atlas",
        "url": "http://127.0.0.1:8000/discovery?preview=datapact.enterprise_metadata_ops.risk_policy_exception_register",
        "readyState": "complete",
        "viewport": {
          "width": 3037,
          "height": 1269,
          "devicePixelRatio": 1
        },
        "scroll": {
          "documentHeight": 1269,
          "documentWidth": 3037,
          "hasVerticalOverflow": false,
          "hasHorizontalOverflow": false
        },
        "shell": {
          "top": 0,
          "left": 298,
          "right": 3037,
          "bottom": 70,
          "width": 2739,
          "height": 70
        },
        "sideRail": {
          "top": 0,
          "left": 0,
          "right": 298,
          "bottom": 1269,
          "width": 298,
          "height": 1269
        },
        "main": {
          "top": 70,
          "left": 298,
          "right": 3037,
          "bottom": 1269,
          "width": 2739,
          "height": 1199
        },
        "mainScroll": {
          "scrollTop": 0,
          "scrollHeight": 6632,
          "clientHeight": 1199,
          "hasOverflow": true
        },
        "home": null,
        "discovery": {
          "top": 70,
          "left": 318,
          "right": 2537,
          "bottom": 6702.453125,
          "width": 2219,
          "height": 6632.453125
        },
        "entity": null,
        "lineage": null,
        "lineagePrototype": {
          "page": null,
          "hero": null,
          "workbench": null,
          "graph": null
        },
        "audit": {
          "page": null,
          "shell": null,
          "main": null,
          "table": null,
          "mainStyle": null,
          "shellStyle": null
        },
        "admin": {
          "page": null,
          "shell": null,
          "main": null
        },
        "textPreview": "Governance Atlas BY ENTRADA GOVERN Command Center Discover Stewardship KNOWLEDGE Glossary & CDEs Lineage Atlas TRUST Audit Evidence Control Center S Skyler Admin Workspace › datapact.atlas ⌘K UC connected · 100% coverage Atlas AI WORKSPACE-SCOPED METADATA Workspace-scoped app-principal view; actor-scoped protected reads stay restricted. CERTIFICATION 50 results Certified 44 In Review 0 Uncertified 0 Draft 3 DOMAIN Customer 11 Finance 17 Marketing 6 Operations 3 People 1 Product 6 CLASSIFICATION Confidential 45 Internal 1 Restricted 4 ATTRIBUTES Critical Data Element Contains PII No PII DISCOVER Find trusted, governed data Search across catalogs, schemas, tables, columns, models, and glossary terms. Workspace-scoped results use Unity Catalog and governance store signals; actor-scoped protected reads remain restricted. Saved searches Advanced Showing 50 of 50 assets Sort: Relevance risk_policy_exception_register datapact.enterprise_metadata_ops.risk_policy_exception_register Certified 100% 100% Restricted — Aggregated policy-exception register derived from Cotality lien records. Risk Steward ⋮ Open Record Open lineage Certified risk_data_quality_review datapact.enterprise_metadata_ops.risk_data_quality_review Draft 100% 100% Restricted — Aggregated data-quality review signal derived from Cotality market records. Risk Steward ⋮ Open Record Open lineage Draft operations_certification_backlog datapact.enterprise_metadata_ops.operations_certification_backlog Draft 100% 100% Confidential — Aggregated certification backlog signal derived from Cotality transfer records. Operations S",
        "controls": [
          {
            "text": "Command Center",
            "disabled": false,
            "aria": ""
          },
          {
            "text": "Discover",
            "disabled": false,
            "aria": ""
          },
          {
            "text": "Stewardship",
            "disabled": false,
            "aria": ""
          },
          {
            "text": "Glossary & CDEs",
            "disabled": false,
            "aria": ""
          },
          {
            "text": "Lineage Atlas",
            "disabled": false,
            "aria": ""
          },
          {
            "text": "Audit Evidence",
            "disabled": false,
            "aria": ""
          },
          {
            "text": "Control Center",
            "disabled": false,
            "aria": ""
          },
          {
            "text": "S Skyler Admin",
            "disabled": false,
            "aria": "Open profile menu for Skyler"
          },
          {
            "text": "Workspace › datapact.atlas",
            "disabled": false,
            "aria": "Open Governance Atlas Command Center"
          },
          {
            "text": "Submit global search unavailable: enter a search term.",
            "disabled": true,
            "aria": "Submit global search unavailable: enter a search term."
          },
          {
            "text": "Notifications",
            "disabled": false,
            "aria": "Notifications"
          },
          {
            "text": "Help",
            "disabled": false,
            "aria": "Help"
          },
          {
            "text": "Atlas AI",
            "disabled": false,
            "aria": ""
          },
          {
            "text": "Certified 44",
            "disabled": false,
            "aria": ""
          },
          {
            "text": "In Review 0",
            "disabled": false,
            "aria": ""
          },
          {
            "text": "Uncertified 0",
            "disabled": false,
            "aria": ""
          },
          {
            "text": "Draft 3",
            "disabled": false,
            "aria": ""
          },
          {
            "text": "Customer 11",
            "disabled": false,
            "aria": ""
          },
          {
            "text": "Finance 17",
            "disabled": false,
            "aria": ""
          },
          {
            "text": "Marketing 6",
            "disabled": false,
            "aria": ""
          },
          {
            "text": "Operations 3",
            "disabled": false,
            "aria": ""
          },
          {
            "text": "People 1",
            "disabled": false,
            "aria": ""
          },
          {
            "text": "Product 6",
            "disabled": false,
            "aria": ""
          },
          {
            "text": "Confidential 45",
            "disabled": false,
            "aria": ""
          },
          {
            "text": "Internal 1",
            "disabled": false,
            "aria": ""
          },
          {
            "text": "Restricted 4",
            "disabled": false,
            "aria": ""
          },
          {
            "text": "Critical Data Element",
            "disabled": false,
            "aria": ""
          },
          {
            "text": "Contains PII",
            "disabled": false,
            "aria": ""
          },
          {
            "text": "No PII",
            "disabled": false,
            "aria": ""
          },
          {
            "text": "Saved searches",
            "disabled": false,
            "aria": ""
          },
          {
            "text": "Advanced",
            "disabled": false,
            "aria": ""
          },
          {
            "text": "Relevance",
            "disabled": false,
            "aria": ""
          },
          {
            "text": "Grid view",
            "disabled": false,
            "aria": "Grid view"
          },
          {
            "text": "List view",
            "disabled": false,
            "aria": "List view"
          },
          {
            "text": "risk_policy_exception_register",
            "disabled": false,
            "aria": ""
          },
          {
            "text": "Open Record",
            "disabled": false,
            "aria": "Open Record"
          },
          {
            "text": "Open lineage",
            "disabled": false,
            "aria": "Open Lineage"
          },
          {
            "text": "risk_data_quality_review",
            "disabled": false,
            "aria": ""
          },
          {
            "text": "Open Record",
            "disabled": false,
            "aria": "Open Record"
          },
          {
            "text": "Open lineage",
            "disabled": false,
            "aria": "Open Lineage"
          },
          {
            "text": "operations_certification_backlog",
            "disabled": false,
            "aria": ""
          },
          {
            "text": "Open Record",
            "disabled": false,
            "aria": "Open Record"
          },
          {
            "text": "Open lineage",
            "disabled": false,
            "aria": "Open Lineage"
          },
          {
            "text": "finance_exception_review",
            "disabled": false,
            "aria": ""
          },
          {
            "text": "Open Record",
            "disabled": false,
            "aria": "Open Record"
          },
          {
            "text": "Open lineage",
            "disabled": false,
            "aria": "Open Lineage"
          },
          {
            "text": "customer_stewardship_queue",
            "disabled": false,
            "aria": ""
          },
          {
            "text": "Open Record",
            "disabled": false,
            "aria": "Open Record"
          },
          {
            "text": "Open lineage",
            "disabled": false,
            "aria": "Open Lineage"
          },
          {
            "text": "sales_pipeline_revenue",
            "disabled": false,
            "aria": ""
          },
          {
            "text": "Open Record",
            "disabled": false,
            "aria": "Open Record"
          },
          {
            "text": "Open lineage",
            "disabled": false,
            "aria": "Open Lineage"
          },
          {
            "text": "revenue_booking_bridge",
            "disabled": false,
            "aria": ""
          },
          {
            "text": "Open Record",
            "disabled": false,
            "aria": "Open Record"
          },
          {
            "text": "Open lineage",
            "disabled": false,
            "aria": "Open Lineage"
          },
          {
            "text": "orders",
            "disabled": false,
            "aria": ""
          },
          {
            "text": "Open Record",
            "disabled": false,
            "aria": "Open Record"
          },
          {
            "text": "Open lineage",
            "disabled": false,
            "aria": "Open Lineage"
          },
          {
            "text": "revenue_product_signal",
            "disabled": false,
            "aria": ""
          },
          {
            "text": "Open Record",
            "disabled": false,
            "aria": "Open Record"
          },
          {
            "text": "Open lineage",
            "disabled": false,
            "aria": "Open Lineage"
          },
          {
            "text": "product_revenue_experiment_feed",
            "disabled": false,
            "aria": ""
          },
          {
            "text": "Open Record",
            "disabled": false,
            "aria": "Open Record"
          },
          {
            "text": "Open lineage",
            "disabled": false,
            "aria": "Open Lineage"
          },
          {
            "text": "clickstream_events",
            "disabled": false,
            "aria": ""
          },
          {
            "text": "Open Record",
            "disabled": false,
            "aria": "Open Record"
          },
          {
            "text": "Open lineage",
            "disabled": false,
            "aria": "Open Lineage"
          },
          {
            "text": "revenue_attribution_snapshot",
            "disabled": false,
            "aria": ""
          },
          {
            "text": "Open Record",
            "disabled": false,
            "aria": "Open Record"
          },
          {
            "text": "Open lineage",
            "disabled": false,
            "aria": "Open Lineage"
          },
          {
            "text": "campaign_roi_revenue",
            "disabled": false,
            "aria": ""
          },
          {
            "text": "Open Record",
            "disabled": false,
            "aria": "Open Record"
          },
          {
            "text": "Open lineage",
            "disabled": false,
            "aria": "Open Lineage"
          },
          {
            "text": "attribution_daily",
            "disabled": false,
            "aria": ""
          },
          {
            "text": "Open Record",
            "disabled": false,
            "aria": "Open Record"
          },
          {
            "text": "Open lineage",
            "disabled": false,
            "aria": "Open Lineage"
          },
          {
            "text": "compensation_band",
            "disabled": false,
            "aria": ""
          },
          {
            "text": "Open Record",
            "disabled": false,
            "aria": "Open Record"
          },
          {
            "text": "Open lineage",
            "disabled": false,
            "aria": "Open Lineage"
          },
          {
            "text": "payments",
            "disabled": false,
            "aria": ""
          }
        ]
      }
    }
  ],
  "console": [],
  "pageErrors": [],
  "requestFailures": [],
  "checks": {
    "buildMatches": true
  },
  "runtimeStatus": {
    "url": "http://127.0.0.1:8000/api/runtime/status",
    "status": 200,
    "ok": true,
    "buildId": "frontend-39bc0b9be33d",
    "state": "live",
    "actorRole": "Reader",
    "govCatalog": "datapact",
    "govSchema": "atlas"
  },
  "captureCount": 1,
  "interactionCount": 1,
  "consoleErrorCount": 0,
  "pageErrorCount": 0,
  "requestFailureCount": 0,
  "expectedRequestFailureCount": 0,
  "passed": true
}